{"updated": "2026-07-13T00:30:04+0200", "events": [{"at": "2026-07-13T00:30:04+0200", "t": "00:30", "kind": "brain", "text": "brain: 14631 facts \u00b7 hallucinations 0.0% gated", "ok": true}, {"at": "2026-07-12T22:29:50Z", "t": "00:29", "kind": "router", "text": "hard \u2192 cloud  43.0s", "ok": true}, {"at": "2026-07-12T22:29:07Z", "t": "00:29", "kind": "router", "text": "hard \u2192 cloud  3.6s", "ok": true}, {"at": "2026-07-12T22:29:03Z", "t": "00:29", "kind": "router", "text": "hard \u2192 cloud  174.6s", "ok": true}, {"at": "2026-07-12T22:26:55Z", "t": "00:26", "kind": "router", "text": "hard \u2192 cloud  13.6s", "ok": true}, {"at": "2026-07-12T22:26:41Z", "t": "00:26", "kind": "router", "text": "hard \u2192 cloud  12.7s", "ok": true}, {"at": "2026-07-12T22:26:29Z", "t": "00:26", "kind": "router", "text": "hard \u2192 cloud  87.2s", "ok": true}, {"at": "2026-07-12T22:21:38Z", "t": "00:21", "kind": "router", "text": "hard \u2192 cloud  97.6s", "ok": true}, {"at": "2026-07-12T22:20:29Z", "t": "00:20", "kind": "router", "text": "hard \u2192 cloud  27.0s", "ok": true}, {"at": "2026-07-12T22:16:06+00:00", "t": "00:16", "kind": "deploy", "text": "self-improve: Theme essay `<mark>` highlights as a phosphor ", "ok": true}, {"at": "2026-07-12T22:03:13+00:00", "t": "00:03", "kind": "deploy", "text": "self-improve: Give essay `<strong>` emphasis a phosphor-high", "ok": true}, {"at": "2026-07-12T21:49:26+00:00", "t": "23:49", "kind": "deploy", "text": "self-improve: Normalize `tab-size` in rendered code blocks", "ok": true}, {"at": "2026-07-12T21:37:05+00:00", "t": "23:37", "kind": "deploy", "text": "self-improve: Neutralize the decorative essay-glow bleed und", "ok": true}, {"at": "2026-07-12T21:24:21+00:00", "t": "23:24", "kind": "deploy", "text": "self-improve: Frame essay code blocks as a phosphor panel", "ok": true}]}