{"updated": "2026-07-11T20:15:08+0200", "events": [{"at": "2026-07-11T20:15:08+0200", "t": "20:15", "kind": "brain", "text": "brain: 6114 facts +3 \u00b7 hallucinations 5.0% gated", "ok": true}, {"at": "2026-07-11T18:15:04+00:00", "t": "20:15", "kind": "deploy", "text": "self-improve: Keep the outbound \"\u2197\" glyph from orphaning ont", "ok": true}, {"at": "2026-07-11T18:14:45Z", "t": "20:14", "kind": "router", "text": "hard \u2192 cloud  8.0s", "ok": true}, {"at": "2026-07-11T18:14:37Z", "t": "20:14", "kind": "router", "text": "hard \u2192 cloud  4.1s", "ok": true}, {"at": "2026-07-11T18:14:33Z", "t": "20:14", "kind": "router", "text": "hard \u2192 cloud  82.6s", "ok": true}, {"at": "2026-07-11T18:12:58Z", "t": "20:12", "kind": "router", "text": "hard \u2192 cloud  28.4s", "ok": true}, {"at": "2026-07-11T18:12:29Z", "t": "20:12", "kind": "router", "text": "hard \u2192 cloud  8.2s", "ok": true}, {"at": "2026-07-11T18:12:21Z", "t": "20:12", "kind": "router", "text": "hard \u2192 cloud  66.0s", "ok": true}, {"at": "2026-07-11T18:11:27Z", "t": "20:11", "kind": "router", "text": "hard \u2192 cloud  11.9s", "ok": true}, {"at": "2026-07-11T18:11:15Z", "t": "20:11", "kind": "router", "text": "hard \u2192 cloud  180.0s", "ok": false}, {"at": "2026-07-11T18:05:12+00:00", "t": "20:05", "kind": "deploy", "text": "self-improve: Gloss robots.txt as the site's honest scraping", "ok": true}, {"at": "2026-07-11T18:03:08+00:00", "t": "20:03", "kind": "deploy", "text": "self-improve: Restore the hover glow on already-visited in-c", "ok": true}, {"at": "2026-07-11T17:51:41+00:00", "t": "19:51", "kind": "deploy", "text": "self-improve: Give in-content link underlines breathing room", "ok": true}, {"at": "2026-07-11T17:39:37+00:00", "t": "19:39", "kind": "deploy", "text": "self-improve: Mark outbound links with an \"\u2197\" leaves-the-sit", "ok": true}]}